facturama/__init__.py
tests/__init__.py
tests/branch.py
tests/catalogs.py
tests/cfdi.py
tests/cfdiMulti.py
tests/csds.py
tests/csdsMulti.py
tests/customers.py
tests/products.py
facturama-2.0.5.1.dist-info/LICENSE
facturama-2.0.5.1.dist-info/METADATA
facturama-2.0.5.1.dist-info/WHEEL
facturama-2.0.5.1.dist-info/top_level.txt
facturama-2.0.5.1.dist-info/zip-safe
facturama-2.0.5.1.dist-info/RECORD
