Metadata-Version: 2.1
Name: facturama
Version: 2.0.5.1
Summary: Easy Facturama python wrapper
Home-page: https://github.com/tingsystems/facturama
Download-URL: https://github.com/tingsystems/facturama/master
Author: Tingsystems
Author-email: Tingsystems <soporte@tingsystems.com>
License: MIT License
Project-URL: Homepage, https://github.com/tingsystems/facturama
Keywords: facturama,wrapper
Classifier: Development Status :: 5 - Production/Stable
Classifier: Intended Audience :: Developers
Classifier: Natural Language :: English
Classifier: Operating System :: OS Independent
Classifier: Programming Language :: Python
Classifier: Topic :: Internet :: WWW/HTTP :: Dynamic Content
Classifier: License :: OSI Approved :: MIT License
Requires-Python: >=3.8
License-File: LICENSE
Requires-Dist: requests
Requires-Dist: simplejson
Requires-Dist: nose
